pykepler/__init__.py
pykepler/aberration.py
pykepler/constants.py
pykepler/coordinates.py
pykepler/delta_t.py
pykepler/earth_figure.py
pykepler/eclipse.py
pykepler/elp82b.py
pykepler/equisols.py
pykepler/fund_args.py
pykepler/iau2000a_nutation.py
pykepler/iau2006_precession.py
pykepler/julian_date.py
pykepler/libkepler.so
pykepler/magnitude.py
pykepler/moonphase.py
pykepler/mpc_file.py
pykepler/orbital_elements.py
pykepler/parallax.py
pykepler/pluto.py
pykepler/riseset.py
pykepler/sidereal_time.py
pykepler/vsop87.py
pykepler-1.0.1.dist-info/COPYING
pykepler-1.0.1.dist-info/METADATA
pykepler-1.0.1.dist-info/WHEEL
pykepler-1.0.1.dist-info/top_level.txt
pykepler-1.0.1.dist-info/RECORD
